custom_user_tests/migrations/0001_initial.py
custom_user_tests/migrations/__init__.py
custom_user_tests/tests/__init__.py
custom_user_tests/tests/test_custom_user_model.py
django_lazysignup_redux-1.0.0.dist-info/DESCRIPTION.rst
django_lazysignup_redux-1.0.0.dist-info/METADATA
django_lazysignup_redux-1.0.0.dist-info/metadata.json
django_lazysignup_redux-1.0.0.dist-info/namespace_packages.txt
django_lazysignup_redux-1.0.0.dist-info/RECORD
django_lazysignup_redux-1.0.0.dist-info/top_level.txt
django_lazysignup_redux-1.0.0.dist-info/WHEEL
lazysignup/__init__.py
lazysignup/apps.py
lazysignup/backends.py
lazysignup/constants.py
lazysignup/decorators.py
lazysignup/exceptions.py
lazysignup/forms.py
lazysignup/models.py
lazysignup/signals.py
lazysignup/urls.py
lazysignup/utils.py
lazysignup/views.py
lazysignup/management/__init__.py
lazysignup/management/commands/__init__.py
lazysignup/management/commands/remove_expired_users.py
lazysignup/migrations/0001_initial.py
lazysignup/migrations/__init__.py
lazysignup/templates/lazysignup/convert.html
lazysignup/templates/lazysignup/done.html
lazysignup/templatetags/__init__.py
lazysignup/templatetags/lazysignup_tags.py
lazysignup/tests/__init__.py
lazysignup/tests/forms.py
lazysignup/tests/settings.py
lazysignup/tests/test_backend.py
lazysignup/tests/test_manager.py
lazysignup/tests/test_models.py
lazysignup/tests/test_template_tags.py
lazysignup/tests/tests.py
lazysignup/tests/urls.py
lazysignup/tests/views.py
