Metadata-Version: 2.0
Name: django-lazysignup-redux
Version: 1.0.0
Summary: Lazy signup for Django
Home-page: http://github.com/danfairs/django-lazysignup
Author: Dan Fairs
Author-email: dan@fezconsulting.com
License: BSD
Keywords: django lazy signup app user
Platform: UNKNOWN
Classifier: Programming Language :: Python
Classifier: Programming Language :: Python :: 2.7
Classifier: Programming Language :: Python :: 3.3
Classifier: Programming Language :: Python :: 3.4
Classifier: Topic :: Software Development :: Libraries :: Python Modules
Classifier: Framework :: Django
Classifier: Framework :: Django :: 1.7
Classifier: Framework :: Django :: 1.8
Classifier: Development Status :: 4 - Beta
Classifier: License :: OSI Approved :: BSD License
Requires-Dist: setuptools
Requires-Dist: Django (>=1.7)
Requires-Dist: six
Provides-Extra: all
Requires-Dist: Sphinx (>=1.2.2); extra == 'all'
Requires-Dist: sphinx-rtd-theme; extra == 'all'
Requires-Dist: setuptools; extra == 'all'
Requires-Dist: wheel; extra == 'all'
Requires-Dist: coverage (>=3.7.1); extra == 'all'
Requires-Dist: Django (>=1.7); extra == 'all'
Requires-Dist: psycopg2; extra == 'all'
Requires-Dist: flake8 (>=2.2.0); extra == 'all'
Requires-Dist: mock (>=1.0.1); extra == 'all'
Requires-Dist: six; extra == 'all'
Provides-Extra: docs
Requires-Dist: Sphinx (>=1.2.2); extra == 'docs'
Requires-Dist: sphinx-rtd-theme; extra == 'docs'
Provides-Extra: packaging
Requires-Dist: wheel; extra == 'packaging'
Provides-Extra: test
Requires-Dist: coverage (>=3.7.1); extra == 'test'
Requires-Dist: flake8 (>=2.2.0); extra == 'test'
Requires-Dist: mock (>=1.0.1); extra == 'test'
Requires-Dist: psycopg2; extra == 'test'
